pystarworldsturbo/__init__.py
pystarworldsturbo/py.typed
pystarworldsturbo/common/__init__.py
pystarworldsturbo/common/action.py
pystarworldsturbo/common/action_outcome.py
pystarworldsturbo/common/action_result.py
pystarworldsturbo/common/content_type.py
pystarworldsturbo/common/event.py
pystarworldsturbo/common/exceptions.py
pystarworldsturbo/common/extended_action_result.py
pystarworldsturbo/common/identifiable.py
pystarworldsturbo/common/message.py
pystarworldsturbo/common/perception.py
pystarworldsturbo/elements/__init__.py
pystarworldsturbo/elements/actor.py
pystarworldsturbo/elements/actor_appearance.py
pystarworldsturbo/elements/actuator.py
pystarworldsturbo/elements/body.py
pystarworldsturbo/elements/mind.py
pystarworldsturbo/elements/mind_core.py
pystarworldsturbo/elements/sensor.py
pystarworldsturbo/environment/__init__.py
pystarworldsturbo/environment/ambient.py
pystarworldsturbo/environment/environment.py
pystarworldsturbo/environment/location.py
pystarworldsturbo/environment/location_appearance.py
pystarworldsturbo/environment/physics/__init__.py
pystarworldsturbo/environment/physics/action_executor.py
pystarworldsturbo/environment/physics/executor_factory.py
pystarworldsturbo/utils/__init__.py
pystarworldsturbo/utils/utils.py
pystarworldsturbo/utils/json/__init__.py
pystarworldsturbo/utils/json/json_value.py
pystarworldsturbo-1.2.8.dist-info/LICENSE
pystarworldsturbo-1.2.8.dist-info/METADATA
pystarworldsturbo-1.2.8.dist-info/WHEEL
pystarworldsturbo-1.2.8.dist-info/top_level.txt
pystarworldsturbo-1.2.8.dist-info/RECORD
